dicy/__init__.py
dicy/cli.py
dicy/dicy.py
dicy-0.0.3.dist-info/AUTHORS.rst
dicy-0.0.3.dist-info/LICENSE
dicy-0.0.3.dist-info/METADATA
dicy-0.0.3.dist-info/WHEEL
dicy-0.0.3.dist-info/entry_points.txt
dicy-0.0.3.dist-info/top_level.txt
dicy-0.0.3.dist-info/RECORD
